odoo/addons/fleet_vehicle_history_date_end/README.rst
odoo/addons/fleet_vehicle_history_date_end/__init__.py
odoo/addons/fleet_vehicle_history_date_end/__manifest__.py
odoo/addons/fleet_vehicle_history_date_end/i18n/fleet_vehicle_history_date_end.pot
odoo/addons/fleet_vehicle_history_date_end/i18n/it.po
odoo/addons/fleet_vehicle_history_date_end/i18n/pt_BR.po
odoo/addons/fleet_vehicle_history_date_end/models/__init__.py
odoo/addons/fleet_vehicle_history_date_end/models/fleet_vehicle_assignation_log.py
odoo/addons/fleet_vehicle_history_date_end/readme/CONTRIBUTORS.md
odoo/addons/fleet_vehicle_history_date_end/readme/DESCRIPTION.md
odoo/addons/fleet_vehicle_history_date_end/static/description/icon.png
odoo/addons/fleet_vehicle_history_date_end/static/description/index.html
odoo/addons/fleet_vehicle_history_date_end/tests/__init__.py
odoo/addons/fleet_vehicle_history_date_end/tests/test_vehicle_history_date_end.py
odoo_addon_fleet_vehicle_history_date_end-18.0.1.0.0.2.dist-info/METADATA
odoo_addon_fleet_vehicle_history_date_end-18.0.1.0.0.2.dist-info/WHEEL
odoo_addon_fleet_vehicle_history_date_end-18.0.1.0.0.2.dist-info/top_level.txt
odoo_addon_fleet_vehicle_history_date_end-18.0.1.0.0.2.dist-info/RECORD
